{"skeleton":{"hash":"j+tggfA0NzE","spine":"4.1.23","x":-175.43,"y":-29.2,"width":279.84,"height":202.5,"images":"./images/","audio":""},"bones":[{"name":"root","scaleX":0.5,"scaleY":0.5},{"name":"back","parent":"root","length":50,"rotation":90,"color":"b233ffff"},{"name":"capoo_back_046_3","parent":"back","x":274.46,"y":298.31,"color":"b233ffff"}],"slots":[{"name":"capoo_back_046_1","bone":"back","attachment":"capoo_back_046_1"},{"name":"capoo_back_046_2","bone":"back","attachment":"capoo_back_046_2"},{"name":"capoo_back_046_3","bone":"capoo_back_046_3","attachment":"capoo_back_046_3"},{"name":"capoo_back_046_4","bone":"capoo_back_046_3"}],"skins":[{"name":"default","attachments":{"capoo_back_046_1":{"capoo_back_046_1":{"x":144.11,"y":29.69,"rotation":-90,"width":477,"height":405}},"capoo_back_046_2":{"capoo_back_046_2":{"type":"mesh","uvs":[0.18631,0,0.21541,0.00802,0.34407,0.17731,0.504,0.38774,0.7441,0.52287,0.95577,0.58407,1,0.71295,1,0.85173,0.96266,1,0.71627,1,0.50092,0.88521,0.29263,0.77418,0.16852,0.59328,0,0.34765,0,0.0861,0.08968,0],"triangles":[13,14,15,0,13,15,13,1,2,1,13,0,12,2,3,2,12,13,11,12,3,6,4,5,10,11,3,10,3,4,9,10,4,6,9,4,7,9,6,8,9,7],"vertices":[1,2,10.85,-20.77,1,1,2,10.01,-25.31,1,2,1,266.69,252.93,0.22292,2,-7.76,-45.38,0.77708,2,1,244.6,227.98,0.5,2,-29.86,-70.33,0.5,2,1,230.41,190.52,0.74074,2,-44.05,-107.78,0.25926,1,1,223.98,157.5,1,1,1,210.45,150.6,1,1,1,195.88,150.6,1,1,1,180.31,156.43,1,2,1,180.31,194.86,0.74074,2,-94.15,-103.44,0.25926,2,1,192.36,228.46,0.61836,2,-82.09,-69.85,0.38164,2,1,204.02,260.95,0.5,2,-70.44,-37.35,0.5,2,1,223.02,280.31,0.28794,2,-51.44,-17.99,0.71206,1,2,-25.65,8.3,1,1,2,1.81,8.3,1,1,2,10.85,-5.69,1],"hull":16,"edges":[0,30,0,2,6,8,8,10,10,12,12,14,14,16,16,18,26,28,28,30,18,20,20,22,22,24,24,26,2,4,4,6],"width":156,"height":105}},"capoo_back_046_3":{"capoo_back_046_3":{"x":-5.14,"y":-0.44,"rotation":-90,"width":106,"height":103}},"capoo_back_046_4":{"capoo_back_046_4":{"x":9.42,"y":14.97,"rotation":-90,"width":171,"height":198}}}}],"animations":{"animation":{"slots":{"capoo_back_046_1":{"attachment":[{"name":"capoo_back_046_1"},{"time":1.8333,"name":"capoo_back_046_1"}]},"capoo_back_046_2":{"attachment":[{"name":"capoo_back_046_2"},{"time":1.8333,"name":"capoo_back_046_2"}]},"capoo_back_046_3":{"attachment":[{"name":"capoo_back_046_3"},{"time":0.1667},{"time":0.3333,"name":"capoo_back_046_3"},{"time":0.5},{"time":0.6667,"name":"capoo_back_046_3"},{"time":0.8333},{"time":1,"name":"capoo_back_046_3"},{"time":1.1667},{"time":1.3333,"name":"capoo_back_046_3"},{"time":1.5},{"time":1.6667,"name":"capoo_back_046_3"},{"time":1.8333}]},"capoo_back_046_4":{"attachment":[{},{"time":0.1667,"name":"capoo_back_046_4"},{"time":0.3333},{"time":0.5,"name":"capoo_back_046_4"},{"time":0.6667},{"time":0.8333,"name":"capoo_back_046_4"},{"time":1},{"time":1.1667,"name":"capoo_back_046_4"},{"time":1.3333},{"time":1.5,"name":"capoo_back_046_4"},{"time":1.6667},{"time":1.8333}]}},"bones":{"capoo_back_046_3":{"translate":[{"curve":"stepped"},{"time":0.5,"curve":[0.833,0,0.527,-11.3,0.833,0,0.527,-12.25]},{"time":0.8333,"x":-11.3,"y":-12.25,"curve":[1.167,-11.3,0.86,-22.61,1.167,-12.25,0.86,-25.43]},{"time":1.1667,"x":-22.61,"y":-25.43,"curve":[1.5,-22.61,1.194,-39.56,1.5,-25.43,1.194,-52.75]},{"time":1.5,"x":-39.56,"y":-52.75,"curve":[1.833,-39.56,1.527,-45.85,1.833,-52.75,1.527,-59.79]},{"time":1.8333,"x":-45.85,"y":-59.79}]}}},"hide_all":{"slots":{"capoo_back_046_1":{"attachment":[{}]},"capoo_back_046_2":{"attachment":[{}]},"capoo_back_046_3":{"attachment":[{}]},"capoo_back_046_4":{"attachment":[{}]}}}}}