{"skeleton":{"hash":"xM/4INo3yYE","spine":"4.1.23","x":-31.45,"y":-49.79,"width":62.02,"height":206.3,"images":"./images/","audio":"./images/"},"bones":[{"name":"root","scaleX":0.5,"scaleY":0.5},{"name":"prop_r","parent":"root","length":100,"rotation":90,"color":"d338f4ff"}],"slots":[{"name":"capoo_prop_084","bone":"prop_r","attachment":"capoo_prop_084"}],"skins":[{"name":"default","attachments":{"capoo_prop_084":{"capoo_prop_084":{"x":106.73,"y":0.87,"rotation":-89.71,"width":122,"height":412}}}}],"animations":{"animation":{"slots":{"capoo_prop_084":{"attachment":[{"name":"capoo_prop_084"}]}}},"hide_all":{"slots":{"capoo_prop_084":{"attachment":[{}]}}}}}